prexview.py
setup.cfg
setup.py
prexview.egg-info/PKG-INFO
prexview.egg-info/SOURCES.txt
prexview.egg-info/dependency_links.txt
prexview.egg-info/requires.txt
prexview.egg-info/top_level.txt