Metadata-Version: 1.1
Name: prexview
Version: 1.0.1
Summary: A pip library to use PrexView a fast, scalable and very friendly service for programatic HTML, PDF, PNG or JPG generation using JSON or XML data.
Home-page: https://github.com/prexview/prexview-python
Author: PrexView
Author-email: code@prexview.com
License: MIT
Download-URL: https://github.com/prexview/prexview-python/archive/1.0.1.tar.gz
Keywords: xml,json,xml-to-pdf,json-to-pdf
Platform: UNKNOWN
Classifier: Development Status :: 4 - Beta
Classifier: Intended Audience :: Developers
Classifier: Topic :: Software Development :: Build Tools
Classifier: License :: OSI Approved :: MIT License
Classifier: Programming Language :: Python :: 2
Classifier: Programming Language :: Python :: 2.7
Classifier: Programming Language :: Python :: 3
Classifier: Programming Language :: Python :: 3.3
Classifier: Programming Language :: Python :: 3.4
Classifier: Programming Language :: Python :: 3.5
